SuBha_STT/__init__.py
subha_stt-0.1.dist-info/METADATA
subha_stt-0.1.dist-info/WHEEL
subha_stt-0.1.dist-info/top_level.txt
subha_stt-0.1.dist-info/RECORD
